egor_kashpar_16/__init__.py
egor_kashpar_16/config.py
egor_kashpar_16/dataset.py
egor_kashpar_16/features.py
egor_kashpar_16/plots.py
egor_kashpar_16/train_pipeline.py
egor_kashpar_16/entities/__init__.py
egor_kashpar_16/entities/data_params.py
egor_kashpar_16/entities/params.py
egor_kashpar_16/entities/train_params.py
egor_kashpar_16/entities/validate_params.py
egor_kashpar_16/modeling/__init__.py
egor_kashpar_16/modeling/predict.py
egor_kashpar_16/modeling/train.py
egor_kashpar_16/modeling/validate.py
egor_kashpar_16-0.0.3.dist-info/WHEEL
egor_kashpar_16-0.0.3.dist-info/METADATA
egor_kashpar_16-0.0.3.dist-info/RECORD
