Metadata-Version: 2.3
Name: egor_kashpar_16
Version: 0.0.3
Summary: A short description of the project.
Author: Egor Kashpar
Requires-Python: ~=3.11
Classifier: Programming Language :: Python :: 3
